henriqueslab_updater/__init__.py
henriqueslab_updater/__version__.py
henriqueslab_updater/convenience.py
henriqueslab_updater/core/__init__.py
henriqueslab_updater/core/cache_manager.py
henriqueslab_updater/core/update_checker.py
henriqueslab_updater/core/version_compare.py
henriqueslab_updater/detectors/__init__.py
henriqueslab_updater/detectors/install_detector.py
henriqueslab_updater/notifiers/__init__.py
henriqueslab_updater/notifiers/base.py
henriqueslab_updater/notifiers/rich.py
henriqueslab_updater/notifiers/simple.py
henriqueslab_updater/plugins/__init__.py
henriqueslab_updater/plugins/changelog.py
henriqueslab_updater/sources/__init__.py
henriqueslab_updater/sources/base.py
henriqueslab_updater/sources/github.py
henriqueslab_updater/sources/homebrew.py
henriqueslab_updater/sources/pypi.py
henriqueslab_updater/utils/__init__.py
henriqueslab_updater/utils/async_utils.py
henriqueslab_updater/utils/changelog_parser.py
henriqueslab_updater/utils/env_utils.py
henriqueslab_updater/utils/upgrade_executor.py
henriqueslab_updater-1.1.3.dist-info/METADATA
henriqueslab_updater-1.1.3.dist-info/WHEEL
henriqueslab_updater-1.1.3.dist-info/licenses/LICENSE
henriqueslab_updater-1.1.3.dist-info/RECORD
