Metadata-Version: 2.4
Name: henriqueslab-updater
Version: 1.1.3
Summary: Centralized update checking library for HenriquesLab Python packages
Project-URL: Homepage, https://github.com/HenriquesLab/henriqueslab-updater
Project-URL: Repository, https://github.com/HenriquesLab/henriqueslab-updater
Project-URL: Issues, https://github.com/HenriquesLab/henriqueslab-updater/issues
Author-email: HenriquesLab <r.henriques@ucl.ac.uk>
License-Expression: MIT
License-File: LICENSE
Keywords: checker,homebrew,pypi,update,updater,version
Classifier: Development Status :: 4 - Beta
Classifier: Intended Audience :: Developers
Classifier: License :: OSI Approved :: MIT License
Classifier: Programming Language :: Python :: 3
Classifier: Programming Language :: Python :: 3.9
Classifier: Programming Language :: Python :: 3.10
Classifier: Programming Language :: Python :: 3.11
Classifier: Programming Language :: Python :: 3.12
Classifier: Topic :: Software Development :: Libraries
Classifier: Topic :: System :: Software Distribution
Requires-Python: >=3.9
Requires-Dist: packaging>=23.0
Provides-Extra: all
Requires-Dist: httpx>=0.25.0; extra == 'all'
Requires-Dist: rich>=13.0; extra == 'all'
Provides-Extra: dev
Requires-Dist: mypy>=1.7; extra == 'dev'
Requires-Dist: pytest-asyncio>=0.21; extra == 'dev'
Requires-Dist: pytest-cov>=4.0; extra == 'dev'
Requires-Dist: pytest-mock>=3.10; extra == 'dev'
Requires-Dist: pytest>=7.0; extra == 'dev'
Requires-Dist: ruff>=0.1.0; extra == 'dev'
Provides-Extra: httpx
Requires-Dist: httpx>=0.25.0; extra == 'httpx'
Provides-Extra: rich
Requires-Dist: rich>=13.0; extra == 'rich'
